{
  "News": [
    {
      "name": "RTU",
      "isFree": true
    },
    {
      "name": "Cheme TV Noticias",
      "isFree": true,
      "website": "https://chemetvnoticias.com/"
    },
    {
      "name": "CORAPE Digital",
      "isFree": true,
      "website": "https://digitaltv.corape.org.ec/"
    },
    {
      "name": "Mario Pinto",
      "isFree": true,
      "website": "https://mpnoticias.com.ec/"
    },
    {
      "name": "PrensaEc",
      "isFree": true,
      "website": "https://prensa.ec/"
    },
    {
      "name": "Ecotel",
      "isFree": true,
      "website": "https://www.ecotel.tv/"
    }
  ],
  "Religious": [
    {
      "name": "TV Universal",
      "isFree": true
    },
    {
      "name": "ABC",
      "isFree": true,
      "website": "https://www.enlace.org/",
      "priority": 9
    },
    {
      "name": "Ficoa",
      "isFree": true,
      "website": "https://iblups.com/ficoatv"
    },
    {
      "name": "IeanJesus Ecuador",
      "isFree": true,
      "website": "http://ieanjesus.org.ec/"
    },
    {
      "name": "TV Universal Ecuador",
      "isFree": true,
      "website": "https://www.universal.org.ec/"
    }
  ],
  "Local": [
    {
      "name": "Zaracay",
      "isFree": true,
      "priority": 4
    }
  ],
  "Entertainment": [
    {
      "name": "Canela",
      "isFree": true,
      "keywords": "canela tv | canelatv",
      "shortName": "CanelaTV"
    },
    {
      "name": "Ecotel",
      "isFree": true,
      "website": "https://www.ecotel.tv/"
    },
    {
      "name": "Ecuador",
      "isFree": true,
      "priority": 9
    },
    {
      "name": "Hechos Ecuador",
      "isFree": true
    },
    {
      "name": "Latacunga",
      "isFree": true,
      "keywords": "latacunga tv | latacungatv"
    },
    {
      "name": "Loreto",
      "isFree": true
    },
    {
      "name": "Multicanal Catamayo",
      "isFree": true
    },
    {
      "name": "Paraíso Digital",
      "isFree": true
    },
    {
      "name": "Pasión",
      "isFree": true
    },
    {
      "name": "Princesa Estéreo",
      "isFree": true
    },
    {
      "name": "Puruwa",
      "isFree": true
    },
    {
      "name": "RTS",
      "isFree": true,
      "priority": 9
    },
    {
      "name": "Teleamazonas",
      "isFree": true,
      "priority": 10
    },
    {
      "name": "Telerama",
      "isFree": true
    },
    {
      "name": "UCSG",
      "isFree": true,
      "website": "https://catomedia.net/"
    },
    {
      "name": "Unisión",
      "isFree": true
    },
    {
      "name": "Wuan+",
      "isFree": true
    },
    {
      "name": "Alfa",
      "isFree": true,
      "website": "https://www.canalalfatv.com/"
    },
    {
      "name": "Ally",
      "isFree": true
    },
    {
      "name": "America Estereo Guayaquil",
      "isFree": true,
      "website": "https://www.americaestereo.com/"
    },
    {
      "name": "America Estereo Ibarra",
      "isFree": true,
      "website": "https://www.americaestereo.com/"
    },
    {
      "name": "America Estereo Quito",
      "isFree": true,
      "website": "https://www.americaestereo.com/"
    },
    {
      "name": "America Estereo Tulcan",
      "isFree": true,
      "website": "https://www.americaestereo.com/"
    },
    {
      "name": "American",
      "isFree": true,
      "website": "https://americantvpelileo.com/"
    },
    {
      "name": "Antel Canal 29",
      "isFree": true,
      "website": "https://antelinternet.odoo.com/"
    },
    {
      "name": "Antena Uno Radiovideo",
      "isFree": true,
      "website": "https://www.antenauno.com/"
    },
    {
      "name": "Arena",
      "isFree": true
    },
    {
      "name": "Asomavision",
      "isFree": true,
      "website": "https://www.asomavision.com/"
    },
    {
      "name": "Austral",
      "isFree": true,
      "website": "https://www.australtv.com/"
    },
    {
      "name": "Bacan Te Veo",
      "isFree": true,
      "website": "https://bacanteveo.com/"
    },
    {
      "name": "Balsero",
      "isFree": true
    },
    {
      "name": "Brisa",
      "isFree": true,
      "website": "https://brisatv23.com/"
    },
    {
      "name": "Britel",
      "isFree": true,
      "website": "https://www.britel.ec/"
    },
    {
      "name": "C6 Television",
      "isFree": true
    },
    {
      "name": "Calidad",
      "isFree": true,
      "website": "https://canalcalidadtv.blogspot.com/"
    },
    {
      "name": "Caluma TV Canal 9",
      "isFree": true,
      "website": "https://www.calumatvcanal9.com/"
    },
    {
      "name": "Canal 9",
      "isFree": true,
      "website": "https://dvnet.ec/"
    },
    {
      "name": "Canal Armonia",
      "isFree": true,
      "website": "https://armoniatv.com/"
    },
    {
      "name": "Canal Star",
      "isFree": true
    },
    {
      "name": "Canal Sur",
      "isFree": true,
      "website": "https://www.loja.gob.ec/contenido/canal-sur"
    },
    {
      "name": "Canal Uno",
      "isFree": true
    },
    {
      "name": "Canar",
      "isFree": true,
      "website": "https://www.canartv.com.ec/"
    },
    {
      "name": "Capital Television",
      "isFree": true
    },
    {
      "name": "Capricho",
      "isFree": true,
      "website": "https://www.caprichotvradio.com/"
    },
    {
      "name": "Cariamanga",
      "isFree": true
    },
    {
      "name": "Centro TV Ecuador",
      "isFree": true,
      "website": "https://centrotvec.blogspot.com/"
    },
    {
      "name": "Chone Vision",
      "isFree": true,
      "website": "https://chonevision.kuffocabletv.com/"
    },
    {
      "name": "CineCable",
      "isFree": true,
      "website": "https://www.cinecabletv.com/",
      "priority": 4
    },
    {
      "name": "Clic",
      "isFree": true,
      "website": "https://clictv.ec/"
    },
    {
      "name": "Cocavision",
      "isFree": true,
      "website": "https://grupococavision.com/"
    },
    {
      "name": "Colorados Vision",
      "isFree": true,
      "website": "https://coloradosvision.com/"
    },
    {
      "name": "Conectate",
      "isFree": true,
      "website": "https://conectate.com.ec/"
    },
    {
      "name": "CONTV Guala",
      "isFree": true
    },
    {
      "name": "Costa",
      "isFree": true,
      "website": "https://intercable.net.ec/tv/"
    },
    {
      "name": "Curiquingue",
      "isFree": true,
      "website": "https://curiquinguetv.com/"
    },
    {
      "name": "Digital",
      "isFree": true
    },
    {
      "name": "Duende",
      "isFree": true,
      "website": "http://duendetv.com/"
    },
    {
      "name": "Duran",
      "isFree": true,
      "website": "https://durantv.com.ec/"
    },
    {
      "name": "Ecovision",
      "isFree": true,
      "website": "https://ecovisiondigital.com/"
    },
    {
      "name": "Ecuavisa",
      "isFree": true,
      "keywords": "ecuavisa -internacional",
      "website": "https://www.ecuavisa.com/",
      "priority": 10
    },
    {
      "name": "Ecuavisa Internacional",
      "isFree": true,
      "website": "https://www.ecuavisa.com/internacional",
      "priority": 9
    },
    {
      "name": "Ecuavision",
      "isFree": true
    },
    {
      "name": "Efinet TV Canal 6",
      "isFree": true,
      "website": "https://www.efinet-tv.com/"
    },
    {
      "name": "ELITE Television",
      "isFree": true,
      "website": "http://eliteradioytelevision.com/"
    },
    {
      "name": "ESTV Canal Peninsular",
      "isFree": true,
      "website": "https://www.estvymediosaliados.com/"
    },
    {
      "name": "Gamavision",
      "isFree": true,
      "website": "https://www.gamavision.com.ec/"
    },
    {
      "name": "Gaviota",
      "isFree": true,
      "website": "https://gaviotatv.com/"
    },
    {
      "name": "Gloriavision",
      "isFree": true,
      "website": "https://gloriavisiontv.com/"
    },
    {
      "name": "GM7 Digital",
      "isFree": true,
      "website": "https://www.vivalivetv.com/channel/gm7-digital"
    },
    {
      "name": "Hatv Gonzanama",
      "isFree": true
    },
    {
      "name": "Imperio TV Canal 6",
      "isFree": true,
      "website": "https://imperiotvcanal6.blogspot.com/"
    },
    {
      "name": "INNTV Canal 3",
      "isFree": true,
      "website": "https://inntvnet.com/"
    },
    {
      "name": "Intercom",
      "isFree": true,
      "website": "https://www.intercom.ec/"
    },
    {
      "name": "Jama",
      "isFree": true,
      "website": "https://jamatv.ec/"
    },
    {
      "name": "Jipitv",
      "isFree": true
    },
    {
      "name": "JUVE Digital",
      "isFree": true
    },
    {
      "name": "KCHTV",
      "isFree": true,
      "website": "https://kchtv.com/"
    },
    {
      "name": "La Mana",
      "isFree": true
    },
    {
      "name": "La Nueva Radio TV 97. 7",
      "isFree": true,
      "website": "http://www.lanuevaradiotv.com/"
    },
    {
      "name": "La Pipol",
      "isFree": true,
      "website": "https://mipipoltv.com/"
    },
    {
      "name": "La Tele",
      "isFree": true,
      "website": "https://www.latele.com.ec/"
    },
    {
      "name": "La Victoria",
      "isFree": true,
      "website": "https://www.lavictoriatv.com/"
    },
    {
      "name": "Loja Television",
      "isFree": true,
      "website": "https://tvloja.com/canal-local"
    },
    {
      "name": "Macara",
      "isFree": true
    },
    {
      "name": "Magica",
      "isFree": true,
      "website": "https://magicatv.ec/"
    },
    {
      "name": "Majestad Television",
      "isFree": true,
      "website": "https://majestadtv.ec/"
    },
    {
      "name": "MakroDigital Television",
      "isFree": true,
      "website": "https://makrodigitaltelevision.com"
    },
    {
      "name": "Manglar",
      "isFree": true
    },
    {
      "name": "Marca",
      "isFree": true,
      "website": "https://marcatv.ec/"
    },
    {
      "name": "Maxivision Canal 8",
      "isFree": true
    },
    {
      "name": "Megavision",
      "isFree": true,
      "website": "https://www.megavisionsa.com/"
    },
    {
      "name": "Mel Radio",
      "isFree": true,
      "website": "https://melradioytv.com/"
    },
    {
      "name": "Monse Teve",
      "isFree": true,
      "website": "https://monsetevehd.com/"
    },
    {
      "name": "Montalvo",
      "isFree": true
    },
    {
      "name": "Multicanal",
      "isFree": true,
      "keywords": "multicanal -catamayo",
      "website": "https://cbvision.net.ec/multicanal/"
    },
    {
      "name": "Nortvision",
      "isFree": true,
      "website": "https://nortvision.tv/"
    },
    {
      "name": "Nuka",
      "isFree": true,
      "website": "https://nukatv.com/"
    },
    {
      "name": "OKTV",
      "isFree": true
    },
    {
      "name": "Ondas Quevedenas",
      "isFree": true
    },
    {
      "name": "Oromar",
      "isFree": true,
      "website": "http://oromartv.com/"
    },
    {
      "name": "Orovision",
      "isFree": true
    },
    {
      "name": "Orva",
      "isFree": true,
      "website": "https://orvatv.com/"
    },
    {
      "name": "OTV Television de Otavalo",
      "isFree": true
    },
    {
      "name": "Palmas",
      "isFree": true
    },
    {
      "name": "Panorama TV Canal 41",
      "isFree": true,
      "website": "https://canal41sd.com/"
    },
    {
      "name": "Paris Radio",
      "isFree": true
    },
    {
      "name": "Pasaje",
      "isFree": true,
      "website": "https://www.pasajetv.com/"
    },
    {
      "name": "Planeta",
      "isFree": true,
      "website": "https://planetaradiotv.com/"
    },
    {
      "name": "Plus",
      "isFree": true,
      "website": "https://plustv.com.ec/"
    },
    {
      "name": "Radio Cima",
      "isFree": true,
      "website": "https://cimaradiotv.com/"
    },
    {
      "name": "Radio La Original",
      "isFree": true,
      "website": "https://www.laoriginaltvradio.com/"
    },
    {
      "name": "RecTV",
      "isFree": true,
      "website": "https://www.rectv.ec/"
    },
    {
      "name": "Red TVE Ventanas",
      "isFree": true
    },
    {
      "name": "REY TV Canal 39",
      "isFree": true
    },
    {
      "name": "Rios Vision Canal 5",
      "isFree": true,
      "website": "https://www.patriciateve.com/canal-5/"
    },
    {
      "name": "RTRTV",
      "isFree": true,
      "website": "https://rtrtv.ec/"
    },
    {
      "name": "RTV",
      "isFree": true,
      "keywords": "rtv -naranjal",
      "website": "https://www.rtvcanaloficial.com/"
    },
    {
      "name": "RTV Naranjal",
      "isFree": true,
      "website": "https://rtvnaranjal.online/"
    },
    {
      "name": "Sacha TV Canal 3",
      "isFree": true
    },
    {
      "name": "Saeta",
      "isFree": true,
      "website": "https://www.saetatvesmeraldas.com/"
    },
    {
      "name": "Satelital TV Canal 6",
      "isFree": true,
      "website": "https://www.satelitaltv.com/"
    },
    {
      "name": "Scandalo",
      "isFree": true,
      "website": "https://scandalotv.com/"
    },
    {
      "name": "Senal Positiva",
      "isFree": true,
      "website": "https://senalpositiva.com/"
    },
    {
      "name": "Sono Onda",
      "isFree": true,
      "website": "https://sonoonda.com/tv-online/"
    },
    {
      "name": "Sonovision",
      "isFree": true,
      "website": "https://miasonovision.ec/"
    },
    {
      "name": "Sucumbios",
      "isFree": true
    },
    {
      "name": "Sumpa",
      "isFree": true,
      "website": "http://www.santaelenacableteve.net"
    },
    {
      "name": "TC Television",
      "isFree": true,
      "website": "https://www.tctelevision.com/"
    },
    {
      "name": "TeleAndina Canal 23",
      "isFree": true
    },
    {
      "name": "Telecosta",
      "isFree": true
    },
    {
      "name": "Teledigital",
      "isFree": true,
      "website": "https://mediosecuador.com/television"
    },
    {
      "name": "Telemar",
      "isFree": true,
      "website": "https://telemartv.com/"
    },
    {
      "name": "TeleMilagro",
      "isFree": true
    },
    {
      "name": "Telepremier Plus",
      "isFree": true,
      "website": "https://telepremier.ec/"
    },
    {
      "name": "Telesucesos",
      "isFree": true,
      "website": "http://www.telesucesos.net/"
    },
    {
      "name": "Television Manabita",
      "isFree": true,
      "website": "https://tvmanabita.tv/"
    },
    {
      "name": "Tenguel TV Canal 2",
      "isFree": true
    },
    {
      "name": "TropicTV Canal 6",
      "isFree": true,
      "website": "https://tropictv.naptelsa.com/"
    },
    {
      "name": "TV 7 Guaranda",
      "isFree": true
    },
    {
      "name": "TV Austro",
      "isFree": true,
      "website": "https://tvaustro.com/"
    },
    {
      "name": "TVC",
      "isFree": true,
      "website": "https://www.tvc.com.ec/"
    },
    {
      "name": "TV Chaco Canal 4",
      "isFree": true
    },
    {
      "name": "TV Chunchi",
      "isFree": true,
      "website": "https://tvchunchi.com/"
    },
    {
      "name": "TV Cisne",
      "isFree": true,
      "website": "https://www.tvcisne.com/"
    },
    {
      "name": "TV Color Canal 36",
      "isFree": true,
      "website": "https://tvcolorcanal36.com/"
    },
    {
      "name": "TV Legislativa",
      "isFree": true,
      "website": "http://tvl.asambleanacional.gob.ec/"
    },
    {
      "name": "TvMas Encuentros",
      "isFree": true,
      "website": "https://tvmas.ec/"
    },
    {
      "name": "TV MICC",
      "isFree": true,
      "website": "https://miccotopaxiec.org/portfolio/tv-micc/"
    },
    {
      "name": "TVN Canal",
      "isFree": true,
      "website": "https://tvncanalhd.com.ec/"
    },
    {
      "name": "TVNet Lago Canal 3",
      "isFree": true,
      "website": "https://tvnetlago.com/"
    },
    {
      "name": "TvOro",
      "isFree": true,
      "website": "http://www.orobla.net"
    },
    {
      "name": "TVS Canal 13",
      "isFree": true,
      "website": "https://tvscanal13.com/"
    },
    {
      "name": "Unicentro Canal 6",
      "isFree": true
    },
    {
      "name": "Unimax",
      "isFree": true
    },
    {
      "name": "Unitv",
      "isFree": true
    },
    {
      "name": "Unsion",
      "isFree": true,
      "website": "https://unsion.tv/"
    },
    {
      "name": "UV Television",
      "isFree": true,
      "website": "https://uvtelevision.com.ec/"
    },
    {
      "name": "Vision al Sur",
      "isFree": true,
      "website": "https://telecomunicacionesdelsur.com.ec/"
    },
    {
      "name": "VitoTVO",
      "isFree": true,
      "website": "https://vitotvo.com/"
    },
    {
      "name": "Yasuni",
      "isFree": true
    },
    {
      "name": "Zu Canal",
      "isFree": true
    },
    {
      "name": "LatacungaTV",
      "isFree": true,
      "website": "https://www.latacungatv.com/"
    }
  ],
  "Education & Culture": [
    {
      "name": "Educa",
      "isFree": true,
      "keywords": "educa tv | educatv",
      "shortName": "EducaTV"
    },
    {
      "name": "AcademiaTV",
      "isFree": true,
      "website": "https://www.academiatv.ec/"
    },
    {
      "name": "Ciracu",
      "isFree": true,
      "website": "https://ciracu.org/"
    },
    {
      "name": "Inti",
      "isFree": true,
      "website": "https://inti.tv/"
    },
    {
      "name": "Manavision",
      "isFree": true,
      "website": "https://www.manavision.ec/"
    },
    {
      "name": "UBE",
      "isFree": true,
      "website": "https://ube.edu.ec/UBE_Tv"
    },
    {
      "name": "UEBI TV Online",
      "isFree": true,
      "website": "https://uebi.online/"
    },
    {
      "name": "UNIANDES",
      "isFree": true,
      "website": "https://uniandestv.com/"
    },
    {
      "name": "UTV",
      "isFree": true,
      "website": "https://www.utn.edu.ec/"
    },
    {
      "name": "UCSG",
      "isFree": true,
      "website": "https://catomedia.net/"
    }
  ],
  "Radios": [
    {
      "name": "El Sol Radio y Television",
      "isFree": true,
      "priority": 4
    },
    {
      "name": "Elite Radio Televisión",
      "isFree": true,
      "priority": 4
    },
    {
      "name": "Radio Impacto 2",
      "isFree": true,
      "priority": 4
    },
    {
      "name": "Visión Radio Televisión",
      "isFree": true,
      "priority": 4
    }
  ],
  "Music Videos": [
    {
      "name": "EcuaMundo Radio",
      "isFree": true,
      "website": "https://ecuamundoradiotv.com/"
    },
    {
      "name": "Ecua Stereo Radio",
      "isFree": true,
      "website": "https://ecuastereo.com/"
    },
    {
      "name": "El Sol Network",
      "isFree": true,
      "website": "https://elsolnetworktv.com/"
    },
    {
      "name": "El Sol",
      "isFree": true,
      "website": "http://www.elsolradiotv.com/"
    },
    {
      "name": "FM Mundo",
      "isFree": true,
      "website": "https://fmmundo.com/fm-mundo-live/"
    },
    {
      "name": "Infinita",
      "isFree": true
    },
    {
      "name": "La Perla Radio",
      "isFree": true,
      "website": "https://radiolaperlatv.com/"
    },
    {
      "name": "Latina Mix Radio",
      "isFree": true,
      "website": "https://latinamixradio.com/"
    },
    {
      "name": "Metropoli Medios",
      "isFree": true,
      "website": "https://metropolimedios.net/"
    },
    {
      "name": "Palmita Radio",
      "isFree": true,
      "website": "https://palmitaradiotvec.com/"
    },
    {
      "name": "PJ Digital Radio",
      "isFree": true
    },
    {
      "name": "Princesa Estereo",
      "isFree": true,
      "website": "https://princesaestereotvlaviajera.com/"
    },
    {
      "name": "Punto Rojo Radio",
      "isFree": true,
      "website": "https://www.radiopuntorojo.com/"
    },
    {
      "name": "Radio Alegria 98.5 FM",
      "isFree": true,
      "website": "https://radioalegriafm.com/"
    },
    {
      "name": "Radio Bonita 106. 7",
      "isFree": true,
      "website": "https://www.bonitalamana.com/"
    },
    {
      "name": "Radio Cuenca Estereo",
      "isFree": true,
      "website": "https://radiocuencaestereo.com/"
    },
    {
      "name": "Radio Fantastica 98.9 FM",
      "isFree": true,
      "website": "http://www.radiofantasticatulcan.com"
    },
    {
      "name": "Radio Monumental",
      "isFree": true,
      "website": "https://www.radiomonumental1510.com/"
    },
    {
      "name": "Radio Online EC",
      "isFree": true,
      "website": "https://radioonline.ec/"
    },
    {
      "name": "Radio Rocafuerte",
      "isFree": true,
      "website": "https://rocafuerteenmarcha.com/"
    },
    {
      "name": "Vos y",
      "isFree": true,
      "website": "https://www.vosytv.com/"
    }
  ],
  "Sports": [
    {
      "name": "El Canal del Futbol",
      "isFree": true,
      "website": "https://www.elcanaldelfutbol.com/"
    },
    {
      "name": "Futbol Ecuatoriano",
      "isFree": true,
      "website": "https://elcanaldelfutbol.com/"
    },
    {
      "name": "GolTV Ecuador",
      "isFree": true,
      "website": "https://ecuador.goltv.tv/"
    },
    {
      "name": "La Redonda",
      "isFree": true,
      "website": "https://laradioredonda.ec/la-redonda-tv/"
    }
  ],
  "Movies & Series": [
    {
      "name": "Pantalla Clasica EC",
      "isFree": true,
      "website": "https://www.radiopasionecuador.com/"
    }
  ]
}